setup.py
bowtor/__init__.py
bowtor.egg-info/PKG-INFO
bowtor.egg-info/SOURCES.txt
bowtor.egg-info/dependency_links.txt
bowtor.egg-info/top_level.txt