Metadata-Version: 1.1
Name: bowtor
Version: 0.0.2
Summary: 快速使用webbrowser查看搜索引擎，非常方便！
Home-page: https://github.com/
Author: Yanming Guo
Author-email: gyms1111@163.com
License: UNKNOWN
Platform: UNKNOWN
Classifier: Programming Language :: Python :: 3
Classifier: License :: OSI Approved :: MIT License
Classifier: Operating System :: OS Independent
